_bimpy.cp36-win_amd64.pyd
bimpy/__init__.py
bimpy/app.py
bimpy/download.py
bimpy/themes.py
bimpy/utils.py
bimpy/multilingual/__init__.py
bimpy/multilingual/load_fonts.py
bimpy/multilingual/unicode_ranges.py
bimpy-0.1.1.dist-info/LICENSE.txt
bimpy-0.1.1.dist-info/METADATA
bimpy-0.1.1.dist-info/WHEEL
bimpy-0.1.1.dist-info/top_level.txt
bimpy-0.1.1.dist-info/RECORD
