Metadata-Version: 2.1
Name: bimpy
Version: 0.1.1
Summary: bimpy - bundled imgui for python
Home-page: https://github.com/podgorskiy/bimpy
Author: Stanislav Pidhorskyi
Author-email: stanislav@podgorskiy.com
License: MIT
